HWNLP/__init__.py
HWNLP/auth_config.py
HWNLP/mt_service.py
HWNLP/nlg_service.py
HWNLP/nlpf_service.py
HWNLP/nlu_service.py
MZAPI-1.0.0.dist-info/LICENSE
MZAPI-1.0.0.dist-info/METADATA
MZAPI-1.0.0.dist-info/WHEEL
MZAPI-1.0.0.dist-info/top_level.txt
MZAPI-1.0.0.dist-info/RECORD
