Metadata-Version: 2.1
Name: MZAPI
Version: 1.0.0
Summary: 米粥SDK
Home-page: https://github.com/xiaomizhoubaobei/XMZAPI
Author: 祁筱欣
Author-email: mzapi@x.mizhoubaobei.top
Classifier: Programming Language :: Python :: 3
Classifier: License :: OSI Approved :: MIT License
Classifier: Operating System :: OS Independent
Requires-Python: >=3.8
License-File: LICENSE
Requires-Dist: huaweicloudsdkcore
Requires-Dist: huaweicloudsdknlp
Requires-Dist: cryptography
